LICENSE
README.md
ansible-inv
setup.py
ansible_inventory/__init__.py
ansible_inventory/config.py
ansible_inventory/globals.py
ansible_inventory/lib.py
ansible_inventory.egg-info/PKG-INFO
ansible_inventory.egg-info/SOURCES.txt
ansible_inventory.egg-info/dependency_links.txt
ansible_inventory.egg-info/requires.txt
ansible_inventory.egg-info/top_level.txt
ansible_inventory/backends/__init__.py
ansible_inventory/frontends/__init__.py