Metadata-Version: 2.1
Name: ansible-inventory
Version: 0.6.7
Summary: Script to manage your Ansible Inventory and also can be used by ansible as a dynamic inventory source
Home-page: https://github.com/diego-treitos/ansible-inventory
Author: Diego Blanco
Author-email: diego.blanco@treitos.com
License: GPLv3
Requires-Python: >=3
License-File: LICENSE
